{
    "mission_name": "compmission",
    "mission": {
        "id": 0,
        "active": false,
        "air_drop_pos": {
            "latitude": 38.145844,
            "longitude": -76.42638
        },
        "home_pos": {
            "latitude": 38.145844,
            "longitude": -76.42638
        },
        "off_axis_odlc_pos": {
            "latitude": 38.141262,
            "longitude": -76.42868
        },
        "emergent_last_known_pos": {
            "latitude": 38.141262,
            "longitude": -76.43199
        },
        "fly_zones": [
            {
                "altitude_msl_min": 100,
                "altitude_msl_max": 800,
                "boundary_pts": [
                    {
                        "order": 0,
                        "latitude": 38.14627,
                        "longitude": -76.42816,
                        "altitude_msl": 0
                    },
                    {
                        "order": 1,
                        "latitude": 38.151627,
                        "longitude": -76.42868,
                        "altitude_msl": 0
                    },
                    {
                        "order": 2,
                        "latitude": 38.15189,
                        "longitude": -76.431465,
                        "altitude_msl": 0
                    },
                    {
                        "order": 3,
                        "latitude": 38.150593,
                        "longitude": -76.43536,
                        "altitude_msl": 0
                    },
                    {
                        "order": 4,
                        "latitude": 38.147568,
                        "longitude": -76.43234,
                        "altitude_msl": 0
                    },
                    {
                        "order": 5,
                        "latitude": 38.144665,
                        "longitude": -76.432945,
                        "altitude_msl": 0
                    },
                    {
                        "order": 6,
                        "latitude": 38.143257,
                        "longitude": -76.43477,
                        "altitude_msl": 0
                    },
                    {
                        "order": 7,
                        "latitude": 38.140465,
                        "longitude": -76.43263,
                        "altitude_msl": 0
                    },
                    {
                        "order": 8,
                        "latitude": 38.14072,
                        "longitude": -76.42601,
                        "altitude_msl": 0
                    },
                    {
                        "order": 9,
                        "latitude": 38.14376,
                        "longitude": -76.4212,
                        "altitude_msl": 0
                    },
                    {
                        "order": 10,
                        "latitude": 38.147346,
                        "longitude": -76.42321,
                        "altitude_msl": 0
                    },
                    {
                        "order": 11,
                        "latitude": 38.14613,
                        "longitude": -76.42665,
                        "altitude_msl": 0
                    }
                ]
            },
            {
                "altitude_msl_min": 100,
                "altitude_msl_max": 800,
                "boundary_pts": [
                    {
                        "order": 0,
                        "latitude": 38.14627,
                        "longitude": -76.42816,
                        "altitude_msl": 0
                    },
                    {
                        "order": 1,
                        "latitude": 38.151627,
                        "longitude": -76.42868,
                        "altitude_msl": 0
                    }
                ]
            }
        ],
        "mission_waypoints": [
            {
                "order": 0,
                "latitude": 38.145313,
                "longitude": -76.42912,
                "altitude_msl": 200
            },
            {
                "order": 1,
                "latitude": 38.149223,
                "longitude": -76.42948,
                "altitude_msl": 300
            },
            {
                "order": 2,
                "latitude": 38.150135,
                "longitude": -76.430855,
                "altitude_msl": 300
            },
            {
                "order": 3,
                "latitude": 38.14895,
                "longitude": -76.43229,
                "altitude_msl": 300
            },
            {
                "order": 4,
                "latitude": 38.14701,
                "longitude": -76.43064,
                "altitude_msl": 400
            },
            {
                "order": 5,
                "latitude": 38.143784,
                "longitude": -76.43199,
                "altitude_msl": 200
            },
            {
                "order": 6,
                "latitude": 38.14293,
                "longitude": -76.4298,
                "altitude_msl": 300
            }
        ],
        "search_grid_points": [
            {
                "order": 0,
                "latitude": 38.143154,
                "longitude": -76.43388,
                "altitude_msl": 300
            },
            {
                "order": 1,
                "latitude": 38.141037,
                "longitude": -76.43199,
                "altitude_msl": 300
            },
            {
                "order": 2,
                "latitude": 38.141262,
                "longitude": -76.42631,
                "altitude_msl": 300
            },
            {
                "order": 3,
                "latitude": 38.143925,
                "longitude": -76.42204,
                "altitude_msl": 300
            },
            {
                "order": 4,
                "latitude": 38.146595,
                "longitude": -76.43199,
                "altitude_msl": 300
            }
        ]
    },
    "obstacles": {
        "moving_obstacles": [
            {
                "sphere_radius": 100,
		"speed_avg": 1,
		"waypoints": [
			{"latitude": 38.145313,
			"longitude": -76.42912,
			"order": 1,
			"altitude_msl": 200
			}
			]
            }
        ],
        "stationary_obstacles": [
            {
                "cylinder_height": 400,
                "latitude": 38.145313,
                "longitude": -76.42912,
                "cylinder_radius": 100
            }
        ]
    },
    "sitlconfig": {
        "takeoff_direction": 0
    },
    "targets": [
    ]
}
